{
  "version": "2.0",
  "sprint_id": "sprint-007",
  "project": "article-engine-plugin",
  "project_path": "C:/Users/USER/Desktop/websites/1-LIVE/SEO Eengine/article-engine-plugin",
  "started_at": "2026-03-29T02:35:41.290Z",
  "last_updated": "2026-03-29T02:44:02.534Z",
  "session_count": 1,
  "status": "completed",
  "current_task": null,
  "execution_order": [
    "VI-003",
    "VI-004",
    "PB-001"
  ],
  "last_protocol_update_at_count": 0,
  "patterns_version": 7,
  "summary": {
    "total": 3,
    "completed": 3,
    "in_progress": 0,
    "blocked": 0,
    "skipped_by_cascade": 0,
    "pending": 0
  },
  "tasks": {
    "VI-003": {
      "title": "Voice Analyzer Agent",
      "type": "API",
      "status": "completed",
      "is_anchor": true,
      "dependencies": [
        "VI-001",
        "VI-002"
      ],
      "started_at": "2026-03-29T02:35:41.291Z",
      "completed_at": "2026-03-29T02:44:02.533Z",
      "reviewer_verdict": "PASS",
      "files_changed": [
        "agents/voice-analyzer.md",
        "agents/draft-writer.md",
        "skills/article-engine/SKILL.md",
        "bridge/server.js",
        "bridge/intelligence/voice-analyzer.js",
        "tests/voice-analyzer-agent.test.js"
      ],
      "verification": {
        "passed": true,
        "skipped": false,
        "output_snippet": "24 tests pass"
      }
    },
    "VI-004": {
      "title": "Dashboard Voice Profiles Page",
      "type": "UI_COMPONENT",
      "status": "completed",
      "is_anchor": false,
      "dependencies": [
        "VI-002"
      ],
      "started_at": "2026-03-29T02:35:41.291Z",
      "completed_at": "2026-03-29T02:44:02.534Z",
      "reviewer_verdict": "PASS",
      "files_changed": [
        "dashboard/src/app/(dashboard)/voice/page.tsx",
        "dashboard/src/components/voice/*.tsx",
        "dashboard/src/lib/api.ts",
        "tests/dashboard-voice.test.js"
      ],
      "verification": {
        "passed": true,
        "skipped": false,
        "output_snippet": "92 tests pass"
      }
    },
    "PB-001": {
      "title": "Universal Article Payload Format",
      "type": "API",
      "status": "completed",
      "is_anchor": false,
      "dependencies": [],
      "started_at": "2026-03-29T02:35:41.291Z",
      "completed_at": "2026-03-29T02:44:02.534Z",
      "reviewer_verdict": "PASS",
      "files_changed": [
        "bridge/publishing/payload.js",
        "bridge/publishing/image-pipeline.js",
        "bridge/publishing/payload-schema.json",
        "bridge/server.js",
        "tests/universal-payload.test.js"
      ],
      "verification": {
        "passed": true,
        "skipped": false,
        "output_snippet": "67 tests pass"
      }
    }
  }
}